ulid_transform/__init__.py
ulid_transform/__init__.pyi
ulid_transform/_py_ulid_impl.py
ulid_transform/_ulid_impl.pyx
ulid_transform/py.typed
ulid_transform/ulid.hh
ulid_transform/ulid_struct.hh
ulid_transform/ulid_uint128.hh
ulid_transform/ulid_wrapper.cpp
ulid_transform/ulid_wrapper.h
ulid_transform/_ulid_impl.cpython-313-x86_64-linux-gnu.so
ulid_transform-1.4.0.dist-info/LICENSE
ulid_transform-1.4.0.dist-info/METADATA
ulid_transform-1.4.0.dist-info/WHEEL
ulid_transform-1.4.0.dist-info/RECORD
