Metadata-Version: 2.3
Name: ulid-transform
Version: 1.4.0
Summary: Create and transform ULIDs
License: MIT
Author: J. Nick Koston
Author-email: nick@koston.org
Requires-Python: >=3.11,<4.0
Classifier: Development Status :: 5 - Production/Stable
Classifier: Intended Audience :: Developers
Classifier: License :: OSI Approved :: MIT License
Classifier: Natural Language :: English
Classifier: Operating System :: OS Independent
Classifier: Programming Language :: Python :: 3
Classifier: Programming Language :: Python :: 3.11
Classifier: Programming Language :: Python :: 3.12
Classifier: Programming Language :: Python :: 3.13
Classifier: Topic :: Software Development :: Libraries
Project-URL: Bug Tracker, https://github.com/bluetooth-devices/ulid-transform/issues
Project-URL: Changelog, https://github.com/bluetooth-devices/ulid-transform/blob/main/CHANGELOG.md
Project-URL: Repository, https://github.com/bluetooth-devices/ulid-transform
